reactivestreams/__init__.py
reactivestreams-0.1.dist-info/DESCRIPTION.rst
reactivestreams-0.1.dist-info/LICENSE.txt
reactivestreams-0.1.dist-info/METADATA
reactivestreams-0.1.dist-info/RECORD
reactivestreams-0.1.dist-info/WHEEL
reactivestreams-0.1.dist-info/metadata.json
reactivestreams-0.1.dist-info/top_level.txt
reactivestreams-0.1.dist-info/zip-safe
